find_similar_and_list/__init__.py
find_similar_and_list/cli.py
find_similar_and_list-0.2.0.dist-info/entry_points.txt
find_similar_and_list-0.2.0.dist-info/WHEEL
find_similar_and_list-0.2.0.dist-info/METADATA
find_similar_and_list-0.2.0.dist-info/RECORD
