Metadata-Version: 2.1
Name: find-similar-and-list
Version: 0.2.0
Summary: 
Home-page: https://github.com/0djentd/find-similar-and-list
Author: 0djentd
Requires-Python: >=3.8,<4.0
Classifier: Programming Language :: Python :: 3
Classifier: Programming Language :: Python :: 3.10
Classifier: Programming Language :: Python :: 3.8
Classifier: Programming Language :: Python :: 3.9
Project-URL: Repository, https://github.com/0djentd/find-similar-and-list
